{"filename":"mhw_odb_severity_en.yml","file_hash":"c5406495ec15cba5d4d2e91eed4060b4462eff3dea7ed2df7bd227e7a6459d80","doc_summary":"OpenAPI Specification: mhw_odb_severity_en.yml","text_chunks":[{"chunk_id":0,"source_page":1,"content_type":"metadata","text":"dataset: marineheatwave\ncollection: mhw\ndoc_type: fact_sheet\ntitle: Marine Heatwave Severity Levels (ODB)\nlang: en\nissuer: \"Ocean Data Bank (ODB), Taiwan\"\ncanonical_url: \"https://eco.odb.ntu.edu.tw/pub/MHW/?lang=en\"\nlicense: \"Unknown\"\nretrieved_at: \"2025-08-25T10:00:00Z\"\ndoc_id: \"mhw-severity-en\"\ntags:\n  - Marine Heatwaves\n  - MHW severity levels\n  - Hobday 2018\n  - classification\npurpose: \"Quick reference for the Hobday et al. (2018) severity levels adopted by ODB Marine Heatwaves.\"\nfaq:\n  - \"How does ODB define moderate vs. strong marine heatwaves?\"\n  - \"What do the MHW level numbers mean?\"\ncontent: |\n  # Marine Heatwave Severity Levels (ODB)\n\n  ODB follows the categorisation defined by [Hobday et al., 2018](https://tos.org/oceanography/article/categorizing-and-naming-marine-heatwaves) when labelling marine heatwave (MHW) events.  The categories compare the observed monthly sea-surface-temperature (SST) anomaly with the local climatological threshold (the 90th percentile seasonal background).\n\n  | Level | Name      | Temperature departure* |\n  | ----- | --------- | ---------------------- |\n  | 0     | None      | SST anomaly below the threshold |\n  | 1     | Moderate  | Threshold ≤ anomaly < threshold + 1 × excess |\n  | 2     | Strong    | Threshold + 1 × excess ≤ anomaly < threshold + 2 × excess |\n  | 3     | Severe    | Threshold + 2 × excess ≤ anomaly < threshold + 3 × excess |\n  | 4     | Extreme   | Anomaly ≥ threshold + 3 × excess |\n\n  *“Excess” refers to the difference between the threshold and the long-term mean SST at that location and month.  Each successive category represents another multiple of that excess above the threshold.\n\n  Key points:\n\n  - **Moderate (Level 1):** anomaly just above the threshold—the earliest indication of an MHW.\n  - **Strong (Level 2):** anomaly at least one extra excess above the threshold.\n  - **Severe (Level 3):** anomaly between two and three excess increments above the threshold.\n  - **Extreme (Level 4):** anomaly at least three excess increments above the threshold.\n\n  These categories are stored in ODB open datasets and are used in downstream tools such as the Hidy Viewer, CSV downloads, and API responses.  Values are reported as integers 0–4 in the `level` field, alongside the underlying SST anomaly in °C.","metadata":{"dataset":"marineheatwave","collection":"mhw","doc_type":"fact_sheet","title":"Marine Heatwave Severity Levels (ODB)","lang":"en","issuer":"Ocean Data Bank (ODB), Taiwan","canonical_url":"https://eco.odb.ntu.edu.tw/pub/MHW/?lang=en","license":"Unknown","retrieved_at":"2025-08-25T10:00:00Z","doc_id":"mhw-severity-en","tags":["Marine Heatwaves","MHW severity levels","Hobday 2018","classification"],"purpose":"Quick reference for the Hobday et al. (2018) severity levels adopted by ODB Marine Heatwaves.","faq":["How does ODB define moderate vs. strong marine heatwaves?","What do the MHW level numbers mean?"],"content":"# Marine Heatwave Severity Levels (ODB)\n\nODB follows the categorisation defined by [Hobday et al., 2018](https://tos.org/oceanography/article/categorizing-and-naming-marine-heatwaves) when labelling marine heatwave (MHW) events.  The categories compare the observed monthly sea-surface-temperature (SST) anomaly with the local climatological threshold (the 90th percentile seasonal background).\n\n| Level | Name      | Temperature departure* |\n| ----- | --------- | ---------------------- |\n| 0     | None      | SST anomaly below the threshold |\n| 1     | Moderate  | Threshold ≤ anomaly < threshold + 1 × excess |\n| 2     | Strong    | Threshold + 1 × excess ≤ anomaly < threshold + 2 × excess |\n| 3     | Severe    | Threshold + 2 × excess ≤ anomaly < threshold + 3 × excess |\n| 4     | Extreme   | Anomaly ≥ threshold + 3 × excess |\n\n*“Excess” refers to the difference between the threshold and the long-term mean SST at that location and month.  Each successive category represents another multiple of that excess above the threshold.\n\nKey points:\n\n- **Moderate (Level 1):** anomaly just above the threshold—the earliest indication of an MHW.\n- **Strong (Level 2):** anomaly at least one extra excess above the threshold.\n- **Severe (Level 3):** anomaly between two and three excess increments above the threshold.\n- **Extreme (Level 4):** anomaly at least three excess increments above the threshold.\n\nThese categories are stored in ODB open datasets and are used in downstream tools such as the Hidy Viewer, CSV downloads, and API responses.  Values are reported as integers 0–4 in the `level` field, alongside the underlying SST anomaly in °C."}}],"artifacts":[{"id":"text_8ab6dab3a1fae658e7824484dfae8bb0260bf6e7","source_file":"bak/temp_uploads/legacy/mhw_odb_severity_en.yml","artifact_type":"text_chunk","metadata":{"dataset":"marineheatwave","collection":"mhw","doc_type":"fact_sheet","title":"Marine Heatwave Severity Levels (ODB)","lang":"en","issuer":"Ocean Data Bank (ODB), Taiwan","canonical_url":"https://eco.odb.ntu.edu.tw/pub/MHW/?lang=en","license":"Unknown","retrieved_at":"2025-08-25T10:00:00Z","doc_id":"mhw-severity-en","tags":["Marine Heatwaves","MHW severity levels","Hobday 2018","classification"],"purpose":"Quick reference for the Hobday et al. (2018) severity levels adopted by ODB Marine Heatwaves.","faq":["How does ODB define moderate vs. strong marine heatwaves?","What do the MHW level numbers mean?"],"content":"# Marine Heatwave Severity Levels (ODB)\n\nODB follows the categorisation defined by [Hobday et al., 2018](https://tos.org/oceanography/article/categorizing-and-naming-marine-heatwaves) when labelling marine heatwave (MHW) events.  The categories compare the observed monthly sea-surface-temperature (SST) anomaly with the local climatological threshold (the 90th percentile seasonal background).\n\n| Level | Name      | Temperature departure* |\n| ----- | --------- | ---------------------- |\n| 0     | None      | SST anomaly below the threshold |\n| 1     | Moderate  | Threshold ≤ anomaly < threshold + 1 × excess |\n| 2     | Strong    | Threshold + 1 × excess ≤ anomaly < threshold + 2 × excess |\n| 3     | Severe    | Threshold + 2 × excess ≤ anomaly < threshold + 3 × excess |\n| 4     | Extreme   | Anomaly ≥ threshold + 3 × excess |\n\n*“Excess” refers to the difference between the threshold and the long-term mean SST at that location and month.  Each successive category represents another multiple of that excess above the threshold.\n\nKey points:\n\n- **Moderate (Level 1):** anomaly just above the threshold—the earliest indication of an MHW.\n- **Strong (Level 2):** anomaly at least one extra excess above the threshold.\n- **Severe (Level 3):** anomaly between two and three excess increments above the threshold.\n- **Extreme (Level 4):** anomaly at least three excess increments above the threshold.\n\nThese categories are stored in ODB open datasets and are used in downstream tools such as the Hidy Viewer, CSV downloads, and API responses.  Values are reported as integers 0–4 in the `level` field, alongside the underlying SST anomaly in °C.","dataset_name":"marineheatwave","raw_doc_type":"fact_sheet"},"links":[],"tags":["Marine Heatwaves","MHW severity levels","Hobday 2018","classification"],"page_number":1,"chunk_index":0,"content_type":"metadata","text":"dataset: marineheatwave\ncollection: mhw\ndoc_type: fact_sheet\ntitle: Marine Heatwave Severity Levels (ODB)\nlang: en\nissuer: \"Ocean Data Bank (ODB), Taiwan\"\ncanonical_url: \"https://eco.odb.ntu.edu.tw/pub/MHW/?lang=en\"\nlicense: \"Unknown\"\nretrieved_at: \"2025-08-25T10:00:00Z\"\ndoc_id: \"mhw-severity-en\"\ntags:\n  - Marine Heatwaves\n  - MHW severity levels\n  - Hobday 2018\n  - classification\npurpose: \"Quick reference for the Hobday et al. (2018) severity levels adopted by ODB Marine Heatwaves.\"\nfaq:\n  - \"How does ODB define moderate vs. strong marine heatwaves?\"\n  - \"What do the MHW level numbers mean?\"\ncontent: |\n  # Marine Heatwave Severity Levels (ODB)\n\n  ODB follows the categorisation defined by [Hobday et al., 2018](https://tos.org/oceanography/article/categorizing-and-naming-marine-heatwaves) when labelling marine heatwave (MHW) events.  The categories compare the observed monthly sea-surface-temperature (SST) anomaly with the local climatological threshold (the 90th percentile seasonal background).\n\n  | Level | Name      | Temperature departure* |\n  | ----- | --------- | ---------------------- |\n  | 0     | None      | SST anomaly below the threshold |\n  | 1     | Moderate  | Threshold ≤ anomaly < threshold + 1 × excess |\n  | 2     | Strong    | Threshold + 1 × excess ≤ anomaly < threshold + 2 × excess |\n  | 3     | Severe    | Threshold + 2 × excess ≤ anomaly < threshold + 3 × excess |\n  | 4     | Extreme   | Anomaly ≥ threshold + 3 × excess |\n\n  *“Excess” refers to the difference between the threshold and the long-term mean SST at that location and month.  Each successive category represents another multiple of that excess above the threshold.\n\n  Key points:\n\n  - **Moderate (Level 1):** anomaly just above the threshold—the earliest indication of an MHW.\n  - **Strong (Level 2):** anomaly at least one extra excess above the threshold.\n  - **Severe (Level 3):** anomaly between two and three excess increments above the threshold.\n  - **Extreme (Level 4):** anomaly at least three excess increments above the threshold.\n\n  These categories are stored in ODB open datasets and are used in downstream tools such as the Hidy Viewer, CSV downloads, and API responses.  Values are reported as integers 0–4 in the `level` field, alongside the underlying SST anomaly in °C."}]}