{"filename":"mhw_zarr_metadata.yml","file_hash":"af4f4099fa5acfaafe9096079c417a53deee1030c4a3c73b14030c396b96a2a7","doc_summary":"OpenAPI Specification: mhw_zarr_metadata.yml","text_chunks":[{"chunk_id":0,"source_page":1,"content_type":"metadata","text":"source_file: data_summaries/mhw_zarr_metadata.yml\ndocument_type: data_summary\ndataset_name: marineheatwave\ncollection: mhw\ntype: Zarr (v2)\ndoc_id: \"b7cea35aac3358af2e52d9f9079779bfdda0fee7\"\ngrid: 0.25\ntimescale: monthly\nretrieved_at: \"2025-08-25T10:00:00Z\"\nrelated_to:\n  - doc_id: [\"d971ef8bbc81997eae74ee0e555588a6526b0ea1\"]\n  - collection: \"mhw\"\nrelated_api: manuals/odb_mhw_openapi.yml\ntags: [dataset, \"MHW metadata\", \"MHW data variables\", 全球海洋熱浪資料集]\ndescription: \"Summary of Zarr metadata for Marine Heatwaves (MHW) 0.25 degree monthly data evaluated from 0.25-degree gridded NOAA OISST v2.1, compiled by Ocean Data Bank (ODB)\"\npurpose: \"The content is the metadata of the Zarr store, which is the dataset where ODB MHW API gets Marine Heatwaves (MHW) data from. From this metadata, we can know the longitude (lon)/latitude (lat) and temporal (date) range of ODB MHW API can get. We also know the data variables (td: Thermal Displacement, sst: Sea surface temperature (SST), sst_anomaly (SST anomalies), and level (MHW levels) stored in this Zarr dataset.\"\nfaq: [\"ODB MHW API資料的時空範圍與尺度?\", \"ODB MHW API如何調用資料\", \"ODB MHW API包含什麼資料、變數或參數\"]\ncontent: |\n  # Usage Note\n  '''\n    本文件提供 ODB MHW API 調用資料時所使用的Zarr資料集的metadata，提供海洋熱浪資料集包括的經緯度(lon, lat)與時間(date)範圍，以及所包含的資料變數，\n    共有td: 海洋熱浪引起的熱位移, sst: 海水表面溫度 (SST), sst_anomaly: 海表溫距平值(異常值; SST anomalies), and level: 海洋熱浪等級，\n    回答ODB MHW API所使用的資料與資料範圍問題(列於faq)應優先引用。\n    This document provides the metadata of the Zarr dataset used by the ODB Marine Heatwaves (MHW) API. \n    It describes the spatial (lon, lat) and temporal (date) coverage, as well as the included variables: \n    td (Thermal Displacement), sst (Sea Surface Temperature), sst_anomaly (SST anomalies), and level (MHW levels). \n    For questions about the ODB MHW API data and the data scale(listed in faq), please refer to this document first.\n    附註：ODB全球海洋熱浪資料庫的更新時間大約為每月18日（依據NOAA OISST資料集實際更新時間而定，有時會延遲），更新至上個月的海洋熱浪資料，\n          以retrieved_at 2025-08-25為例，資料集維度 date 最晚日期即為 2025-07-01，亦即更新至上個月。\n    Remark: The ODB global MHW database is updated around the 18th of each month (depending on the actual update of the NOAA OISST dataset, sometimes delayed). \n            Each update covers data up to the previous month. For example, with retrieved_at = 2025-08-25, the latest date in this dataset is 2025-07-01, meaning data is available up to the previous month.    \n  '''\n\n  <xarray.Dataset> Size: 15GB\n  Dimensions:      (date: 523, lat: 720, lon: 1440)\n  Coordinates:\n    * date         (date) datetime64[ns] 4kB 1982-01-01 1982-02-01 ... 2025-07-01\n    * lat          (lat) float32 3kB -89.88 -89.62 -89.38 ... 89.38 89.62 89.88\n    * lon          (lon) float32 6kB 0.125 0.375 0.625 0.875 ... 359.4 359.6 359.9\n  Data variables:\n      td           (date, lat, lon) float64 4GB dask.array<chunksize=(2, 180, 360), meta=np.ndarray>\n      sst          (date, lat, lon) float32 2GB dask.array<chunksize=(2, 180, 360), meta=np.ndarray>\n      level        (date, lat, lon) int64 4GB dask.array<chunksize=(2, 180, 360), meta=np.ndarray>\n      sst_anomaly  (date, lat, lon) float64 4GB dask.array<chunksize=(2, 180, 360), meta=np.ndarray>","metadata":{"source_file":"data_summaries/mhw_zarr_metadata.yml","document_type":"data_summary","dataset_name":"marineheatwave","collection":"mhw","type":"Zarr (v2)","doc_id":"b7cea35aac3358af2e52d9f9079779bfdda0fee7","grid":0.25,"timescale":"monthly","retrieved_at":"2025-08-25T10:00:00Z","related_to":[{"doc_id":["d971ef8bbc81997eae74ee0e555588a6526b0ea1"]},{"collection":"mhw"}],"related_api":"manuals/odb_mhw_openapi.yml","tags":["dataset","MHW metadata","MHW data variables","全球海洋熱浪資料集"],"description":"Summary of Zarr metadata for Marine Heatwaves (MHW) 0.25 degree monthly data evaluated from 0.25-degree gridded NOAA OISST v2.1, compiled by Ocean Data Bank (ODB)","purpose":"The content is the metadata of the Zarr store, which is the dataset where ODB MHW API gets Marine Heatwaves (MHW) data from. From this metadata, we can know the longitude (lon)/latitude (lat) and temporal (date) range of ODB MHW API can get. We also know the data variables (td: Thermal Displacement, sst: Sea surface temperature (SST), sst_anomaly (SST anomalies), and level (MHW levels) stored in this Zarr dataset.","faq":["ODB MHW API資料的時空範圍與尺度?","ODB MHW API如何調用資料","ODB MHW API包含什麼資料、變數或參數"],"content":"# Usage Note\n'''\n  本文件提供 ODB MHW API 調用資料時所使用的Zarr資料集的metadata，提供海洋熱浪資料集包括的經緯度(lon, lat)與時間(date)範圍，以及所包含的資料變數，\n  共有td: 海洋熱浪引起的熱位移, sst: 海水表面溫度 (SST), sst_anomaly: 海表溫距平值(異常值; SST anomalies), and level: 海洋熱浪等級，\n  回答ODB MHW API所使用的資料與資料範圍問題(列於faq)應優先引用。\n  This document provides the metadata of the Zarr dataset used by the ODB Marine Heatwaves (MHW) API. \n  It describes the spatial (lon, lat) and temporal (date) coverage, as well as the included variables: \n  td (Thermal Displacement), sst (Sea Surface Temperature), sst_anomaly (SST anomalies), and level (MHW levels). \n  For questions about the ODB MHW API data and the data scale(listed in faq), please refer to this document first.\n  附註：ODB全球海洋熱浪資料庫的更新時間大約為每月18日（依據NOAA OISST資料集實際更新時間而定，有時會延遲），更新至上個月的海洋熱浪資料，\n        以retrieved_at 2025-08-25為例，資料集維度 date 最晚日期即為 2025-07-01，亦即更新至上個月。\n  Remark: The ODB global MHW database is updated around the 18th of each month (depending on the actual update of the NOAA OISST dataset, sometimes delayed). \n          Each update covers data up to the previous month. For example, with retrieved_at = 2025-08-25, the latest date in this dataset is 2025-07-01, meaning data is available up to the previous month.    \n'''\n\n<xarray.Dataset> Size: 15GB\nDimensions:      (date: 523, lat: 720, lon: 1440)\nCoordinates:\n  * date         (date) datetime64[ns] 4kB 1982-01-01 1982-02-01 ... 2025-07-01\n  * lat          (lat) float32 3kB -89.88 -89.62 -89.38 ... 89.38 89.62 89.88\n  * lon          (lon) float32 6kB 0.125 0.375 0.625 0.875 ... 359.4 359.6 359.9\nData variables:\n    td           (date, lat, lon) float64 4GB dask.array<chunksize=(2, 180, 360), meta=np.ndarray>\n    sst          (date, lat, lon) float32 2GB dask.array<chunksize=(2, 180, 360), meta=np.ndarray>\n    level        (date, lat, lon) int64 4GB dask.array<chunksize=(2, 180, 360), meta=np.ndarray>\n    sst_anomaly  (date, lat, lon) float64 4GB dask.array<chunksize=(2, 180, 360), meta=np.ndarray>"}}],"artifacts":[{"id":"text_f6ce74aa7f17ca534dcfe54d7b24c7045b6b2d81","source_file":"bak/temp_uploads/legacy/mhw_zarr_metadata.yml","artifact_type":"text_chunk","metadata":{"source_file":"data_summaries/mhw_zarr_metadata.yml","document_type":"data_summary","dataset_name":"marineheatwave","collection":"mhw","type":"Zarr (v2)","doc_id":"b7cea35aac3358af2e52d9f9079779bfdda0fee7","grid":0.25,"timescale":"monthly","retrieved_at":"2025-08-25T10:00:00Z","related_to":[{"doc_id":["d971ef8bbc81997eae74ee0e555588a6526b0ea1"]},{"collection":"mhw"}],"related_api":"manuals/odb_mhw_openapi.yml","tags":["dataset","MHW metadata","MHW data variables","全球海洋熱浪資料集"],"description":"Summary of Zarr metadata for Marine Heatwaves (MHW) 0.25 degree monthly data evaluated from 0.25-degree gridded NOAA OISST v2.1, compiled by Ocean Data Bank (ODB)","purpose":"The content is the metadata of the Zarr store, which is the dataset where ODB MHW API gets Marine Heatwaves (MHW) data from. From this metadata, we can know the longitude (lon)/latitude (lat) and temporal (date) range of ODB MHW API can get. We also know the data variables (td: Thermal Displacement, sst: Sea surface temperature (SST), sst_anomaly (SST anomalies), and level (MHW levels) stored in this Zarr dataset.","faq":["ODB MHW API資料的時空範圍與尺度?","ODB MHW API如何調用資料","ODB MHW API包含什麼資料、變數或參數"],"content":"# Usage Note\n'''\n  本文件提供 ODB MHW API 調用資料時所使用的Zarr資料集的metadata，提供海洋熱浪資料集包括的經緯度(lon, lat)與時間(date)範圍，以及所包含的資料變數，\n  共有td: 海洋熱浪引起的熱位移, sst: 海水表面溫度 (SST), sst_anomaly: 海表溫距平值(異常值; SST anomalies), and level: 海洋熱浪等級，\n  回答ODB MHW API所使用的資料與資料範圍問題(列於faq)應優先引用。\n  This document provides the metadata of the Zarr dataset used by the ODB Marine Heatwaves (MHW) API. \n  It describes the spatial (lon, lat) and temporal (date) coverage, as well as the included variables: \n  td (Thermal Displacement), sst (Sea Surface Temperature), sst_anomaly (SST anomalies), and level (MHW levels). \n  For questions about the ODB MHW API data and the data scale(listed in faq), please refer to this document first.\n  附註：ODB全球海洋熱浪資料庫的更新時間大約為每月18日（依據NOAA OISST資料集實際更新時間而定，有時會延遲），更新至上個月的海洋熱浪資料，\n        以retrieved_at 2025-08-25為例，資料集維度 date 最晚日期即為 2025-07-01，亦即更新至上個月。\n  Remark: The ODB global MHW database is updated around the 18th of each month (depending on the actual update of the NOAA OISST dataset, sometimes delayed). \n          Each update covers data up to the previous month. For example, with retrieved_at = 2025-08-25, the latest date in this dataset is 2025-07-01, meaning data is available up to the previous month.    \n'''\n\n<xarray.Dataset> Size: 15GB\nDimensions:      (date: 523, lat: 720, lon: 1440)\nCoordinates:\n  * date         (date) datetime64[ns] 4kB 1982-01-01 1982-02-01 ... 2025-07-01\n  * lat          (lat) float32 3kB -89.88 -89.62 -89.38 ... 89.38 89.62 89.88\n  * lon          (lon) float32 6kB 0.125 0.375 0.625 0.875 ... 359.4 359.6 359.9\nData variables:\n    td           (date, lat, lon) float64 4GB dask.array<chunksize=(2, 180, 360), meta=np.ndarray>\n    sst          (date, lat, lon) float32 2GB dask.array<chunksize=(2, 180, 360), meta=np.ndarray>\n    level        (date, lat, lon) int64 4GB dask.array<chunksize=(2, 180, 360), meta=np.ndarray>\n    sst_anomaly  (date, lat, lon) float64 4GB dask.array<chunksize=(2, 180, 360), meta=np.ndarray>","title":"OpenAPI Specification: mhw_zarr_metadata.yml","doc_type":"api_spec"},"links":[],"tags":["dataset","MHW metadata","MHW data variables","全球海洋熱浪資料集"],"page_number":1,"chunk_index":0,"content_type":"metadata","text":"source_file: data_summaries/mhw_zarr_metadata.yml\ndocument_type: data_summary\ndataset_name: marineheatwave\ncollection: mhw\ntype: Zarr (v2)\ndoc_id: \"b7cea35aac3358af2e52d9f9079779bfdda0fee7\"\ngrid: 0.25\ntimescale: monthly\nretrieved_at: \"2025-08-25T10:00:00Z\"\nrelated_to:\n  - doc_id: [\"d971ef8bbc81997eae74ee0e555588a6526b0ea1\"]\n  - collection: \"mhw\"\nrelated_api: manuals/odb_mhw_openapi.yml\ntags: [dataset, \"MHW metadata\", \"MHW data variables\", 全球海洋熱浪資料集]\ndescription: \"Summary of Zarr metadata for Marine Heatwaves (MHW) 0.25 degree monthly data evaluated from 0.25-degree gridded NOAA OISST v2.1, compiled by Ocean Data Bank (ODB)\"\npurpose: \"The content is the metadata of the Zarr store, which is the dataset where ODB MHW API gets Marine Heatwaves (MHW) data from. From this metadata, we can know the longitude (lon)/latitude (lat) and temporal (date) range of ODB MHW API can get. We also know the data variables (td: Thermal Displacement, sst: Sea surface temperature (SST), sst_anomaly (SST anomalies), and level (MHW levels) stored in this Zarr dataset.\"\nfaq: [\"ODB MHW API資料的時空範圍與尺度?\", \"ODB MHW API如何調用資料\", \"ODB MHW API包含什麼資料、變數或參數\"]\ncontent: |\n  # Usage Note\n  '''\n    本文件提供 ODB MHW API 調用資料時所使用的Zarr資料集的metadata，提供海洋熱浪資料集包括的經緯度(lon, lat)與時間(date)範圍，以及所包含的資料變數，\n    共有td: 海洋熱浪引起的熱位移, sst: 海水表面溫度 (SST), sst_anomaly: 海表溫距平值(異常值; SST anomalies), and level: 海洋熱浪等級，\n    回答ODB MHW API所使用的資料與資料範圍問題(列於faq)應優先引用。\n    This document provides the metadata of the Zarr dataset used by the ODB Marine Heatwaves (MHW) API. \n    It describes the spatial (lon, lat) and temporal (date) coverage, as well as the included variables: \n    td (Thermal Displacement), sst (Sea Surface Temperature), sst_anomaly (SST anomalies), and level (MHW levels). \n    For questions about the ODB MHW API data and the data scale(listed in faq), please refer to this document first.\n    附註：ODB全球海洋熱浪資料庫的更新時間大約為每月18日（依據NOAA OISST資料集實際更新時間而定，有時會延遲），更新至上個月的海洋熱浪資料，\n          以retrieved_at 2025-08-25為例，資料集維度 date 最晚日期即為 2025-07-01，亦即更新至上個月。\n    Remark: The ODB global MHW database is updated around the 18th of each month (depending on the actual update of the NOAA OISST dataset, sometimes delayed). \n            Each update covers data up to the previous month. For example, with retrieved_at = 2025-08-25, the latest date in this dataset is 2025-07-01, meaning data is available up to the previous month.    \n  '''\n\n  <xarray.Dataset> Size: 15GB\n  Dimensions:      (date: 523, lat: 720, lon: 1440)\n  Coordinates:\n    * date         (date) datetime64[ns] 4kB 1982-01-01 1982-02-01 ... 2025-07-01\n    * lat          (lat) float32 3kB -89.88 -89.62 -89.38 ... 89.38 89.62 89.88\n    * lon          (lon) float32 6kB 0.125 0.375 0.625 0.875 ... 359.4 359.6 359.9\n  Data variables:\n      td           (date, lat, lon) float64 4GB dask.array<chunksize=(2, 180, 360), meta=np.ndarray>\n      sst          (date, lat, lon) float32 2GB dask.array<chunksize=(2, 180, 360), meta=np.ndarray>\n      level        (date, lat, lon) int64 4GB dask.array<chunksize=(2, 180, 360), meta=np.ndarray>\n      sst_anomaly  (date, lat, lon) float64 4GB dask.array<chunksize=(2, 180, 360), meta=np.ndarray>"}]}